golib/__debug__.py
golib/__init__.py
golib/__pycache__/__init__.cpython-37.pyc
golib-2022.2.23.dist-info/LICENSE
golib-2022.2.23.dist-info/METADATA
golib-2022.2.23.dist-info/WHEEL
golib-2022.2.23.dist-info/entry_points.txt
golib-2022.2.23.dist-info/top_level.txt
golib-2022.2.23.dist-info/RECORD
